aws_tmp_keys_fetcher/__init__.py
aws_tmp_keys_fetcher/__main__.py
aws_tmp_keys_fetcher/cli.py
pyproject.toml
aws_tmp_keys_fetcher-0.0.5.dist-info/entry_points.txt
aws_tmp_keys_fetcher-0.0.5.dist-info/LICENSE
aws_tmp_keys_fetcher-0.0.5.dist-info/WHEEL
aws_tmp_keys_fetcher-0.0.5.dist-info/METADATA
aws_tmp_keys_fetcher-0.0.5.dist-info/RECORD
