Metadata-Version: 2.1
Name: aws-tmp-keys-fetcher
Version: 0.0.5
Summary: AWS temporary keys fetcher - simple command-line tool to fetch temporary aws credentials and stores them in your configs so that third party that require actual access keys can work with them.
Home-page: https://github.com/gercograndia/aws-tmp-keys-fetcher
License: MIT
Keywords: AWS,IAM,Temporary,Credentials
Author: Gerco Grandia
Author-email: gerco.grandia@4synergy.nl
Requires-Python: >=3.7,<4.0
Classifier: License :: OSI Approved :: MIT License
Classifier: Programming Language :: Python :: 3
Classifier: Programming Language :: Python :: 3.7
Classifier: Programming Language :: Python :: 3.8
Classifier: Programming Language :: Python :: 3.9
Requires-Dist: boto3 (>=1.12.22,<2.0.0)
Requires-Dist: click (>=7.1.1,<8.0.0)
Requires-Dist: configparser (>=5.0.1,<6.0.0)
Requires-Dist: outdated (>=0.2.0,<0.3.0)
Project-URL: Documentation, https://github.com/gercograndia/aws-tmp-keys-fetcher/blob/master/README.md
Project-URL: Repository, https://github.com/gercograndia/aws-tmp-keys-fetcher
Project-URL: issues, https://github.com/gercograndia/aws-tmp-keys-fetcher/issues
